odoo/addons/pos_payment_method_cashdro/README.rst
odoo/addons/pos_payment_method_cashdro/__init__.py
odoo/addons/pos_payment_method_cashdro/__manifest__.py
odoo/addons/pos_payment_method_cashdro/i18n/it.po
odoo/addons/pos_payment_method_cashdro/i18n/pos_payment_method_cashdro.pot
odoo/addons/pos_payment_method_cashdro/migrations/14.0.1.0.0/pre-migration.py
odoo/addons/pos_payment_method_cashdro/models/__init__.py
odoo/addons/pos_payment_method_cashdro/models/pos_payment_method.py
odoo/addons/pos_payment_method_cashdro/readme/CONFIGURE.rst
odoo/addons/pos_payment_method_cashdro/readme/CONTRIBUTORS.rst
odoo/addons/pos_payment_method_cashdro/readme/DESCRIPTION.rst
odoo/addons/pos_payment_method_cashdro/readme/ROADMAP.rst
odoo/addons/pos_payment_method_cashdro/readme/USAGE.rst
odoo/addons/pos_payment_method_cashdro/static/description/icon.png
odoo/addons/pos_payment_method_cashdro/static/description/index.html
odoo/addons/pos_payment_method_cashdro/static/description/logo.png
odoo/addons/pos_payment_method_cashdro/static/src/js/models.js
odoo/addons/pos_payment_method_cashdro/static/src/js/payment_cashdro.js
odoo/addons/pos_payment_method_cashdro/views/assets.xml
odoo/addons/pos_payment_method_cashdro/views/pos_payment_method_views.xml
odoo14_addon_pos_payment_method_cashdro-14.0.1.0.1.dist-info/METADATA
odoo14_addon_pos_payment_method_cashdro-14.0.1.0.1.dist-info/WHEEL
odoo14_addon_pos_payment_method_cashdro-14.0.1.0.1.dist-info/top_level.txt
odoo14_addon_pos_payment_method_cashdro-14.0.1.0.1.dist-info/RECORD
